civic_jabber_ingest/__init__.py
civic_jabber_ingest/__version__.py
civic_jabber_ingest/cli.py
civic_jabber_ingest/config/__init__.py
civic_jabber_ingest/config/newspaper.yml
civic_jabber_ingest/config/states.yml
civic_jabber_ingest/external_services/__init__.py
civic_jabber_ingest/external_services/news_api.py
civic_jabber_ingest/external_services/newspaper.py
civic_jabber_ingest/external_services/open_states.py
civic_jabber_ingest/legislation/__init__.py
civic_jabber_ingest/legislation/open_states.py
civic_jabber_ingest/models/__init__.py
civic_jabber_ingest/models/article.py
civic_jabber_ingest/models/base.py
civic_jabber_ingest/models/contact.py
civic_jabber_ingest/models/legislator.py
civic_jabber_ingest/models/regulation.py
civic_jabber_ingest/regs/__init__.py
civic_jabber_ingest/regs/va.py
civic_jabber_ingest/schemas/__init__.py
civic_jabber_ingest/schemas/contact.xml
civic_jabber_ingest/schemas/regulation.xml
civic_jabber_ingest/schemas/regulation.xsd
civic_jabber_ingest/utils/__init__.py
civic_jabber_ingest/utils/config.py
civic_jabber_ingest/utils/data_cleaning.py
civic_jabber_ingest/utils/database.py
civic_jabber_ingest/utils/environ.py
civic_jabber_ingest/utils/scrape.py
civic_jabber_ingest/utils/xml.py
civic_jabber_ingest-0.1.0.dist-info/LICENSE
civic_jabber_ingest-0.1.0.dist-info/METADATA
civic_jabber_ingest-0.1.0.dist-info/WHEEL
civic_jabber_ingest-0.1.0.dist-info/entry_points.txt
civic_jabber_ingest-0.1.0.dist-info/top_level.txt
civic_jabber_ingest-0.1.0.dist-info/RECORD
