Metadata-Version: 2.1
Name: civic-jabber-ingest
Version: 0.1.0
Summary: Utilities for ingesting legislative data
Home-page: UNKNOWN
Author: Civic Jabber
Author-email: matt@civicjabber.com
License: UNKNOWN
Platform: UNKNOWN
Requires-Dist: beautifulsoup4 (==4.9.1)
Requires-Dist: certifi (==2020.6.20)
Requires-Dist: chardet (==3.0.4)
Requires-Dist: click (==7.1.2)
Requires-Dist: cssselect (==1.1.0)
Requires-Dist: feedfinder2 (==0.0.4)
Requires-Dist: feedparser (==6.0.1)
Requires-Dist: idna (==2.10)
Requires-Dist: jieba3k (==0.35.1)
Requires-Dist: jinja2 (==2.11.2)
Requires-Dist: joblib (==0.17.0)
Requires-Dist: lxml (==4.5.2)
Requires-Dist: markupsafe (==1.1.1)
Requires-Dist: newspaper3k (==0.2.8)
Requires-Dist: nltk (==3.5)
Requires-Dist: numpy (==1.19.1)
Requires-Dist: pandas (==1.1.0)
Requires-Dist: pillow (==7.2.0)
Requires-Dist: psycopg2-binary (==2.8.6)
Requires-Dist: python-dateutil (==2.8.1)
Requires-Dist: pytz (==2020.1)
Requires-Dist: pyyaml (==5.3.1)
Requires-Dist: regex (==2020.9.27)
Requires-Dist: requests-file (==1.5.1)
Requires-Dist: requests (==2.24.0)
Requires-Dist: sgmllib3k (==1.0.0)
Requires-Dist: six (==1.15.0)
Requires-Dist: soupsieve (==2.0.1)
Requires-Dist: tinysegmenter (==0.3)
Requires-Dist: tldextract (==2.2.3)
Requires-Dist: tqdm (==4.49.0)
Requires-Dist: urllib3 (==1.25.10)
